<?xml version='1.0' encoding='utf-8'?>
<resources>
    <string name="gms_core_dialog_dismiss_text">Don\'t show again</string>
    <string name="revanced_debug_protobuffer_summary">Includes proto buffer in the debug log.</string>
    <string name="revanced_debug_protobuffer_title">Log protocol buffer</string>
    <string name="revanced_debug_spannable_summary">Includes spannable in the debug log.</string>
    <string name="revanced_debug_spannable_title">Log spannable</string>
    <string name="revanced_debug_summary">Prints the debug log.</string>
    <string name="revanced_debug_title">Enable debug logging</string>
    <string name="revanced_disable_music_video_in_album_summary">"When a non-premium user plays a song included in an album, the music video is sometimes played instead of the official song.

Find the official song if a music video is detected playing from an album.

Limitations: Kids videos may not redirected."</string>
    <string name="revanced_disable_quic_protocol_summary">"Disables CronetEngine's QUIC protocol."</string>
    <string name="revanced_disable_quic_protocol_title">Disable QUIC protocol</string>
    <string name="revanced_enable_comments_scroll_top_summary">"Clicking on the comment panel title ('Comments') scrolls to the top.

Limitations: Does not apply to comment replies."</string>
    <string name="revanced_enable_comments_scroll_top_title">Enable scroll to top in comments</string>
    <string name="revanced_gms_show_dialog_summary">Displays the optimization dialog for GMSCore at each application startup.</string>
    <string name="revanced_gms_show_dialog_title">Show optimization dialog for GMSCore</string>
    <string name="revanced_hide_search_button_summary">Hides the search button in the toolbar.</string>
    <string name="revanced_hide_search_button_title">Hide search button</string>
    <string name="revanced_hide_settings_menu_summary">"Hide elements of the settings menu.
This hides not only the YT Music settings menu, but also the ReVanced Extended settings menu."</string>
    <string name="revanced_hide_settings_menu_title">Hide settings menu</string>
    <string name="revanced_litho_layout_thread_pool_max_size_entry_0">Not overridden</string>
    <string name="revanced_litho_layout_thread_pool_max_size_invalid_toast">Litho thread pool max size must be between 1-3.</string>
    <string name="revanced_litho_layout_thread_pool_max_size_summary">"Changes the max size of the Litho thread pool.

A larger value may improve the performance of loading Litho layouts, but may drain more battery."</string>
    <string name="revanced_litho_layout_thread_pool_max_size_title">Litho thread pool max size</string>
    <string name="revanced_replace_navigation_button_about_summary">"This feature is experimental.
There are structural limitations of the patch, as Activities such as Search and Settings in YouTube Music are not public.

Known issues:
• When a replaced Activity such as Search and Settings is closed, the start page opens.

Click to open the 'Change start page' settings."</string>
    <string name="revanced_replace_navigation_button_about_title">About replace button</string>
    <string name="revanced_replace_navigation_samples_button_summary">Replaces the Samples button with the Search button.</string>
    <string name="revanced_replace_navigation_samples_button_title">Replace Samples button</string>
    <string name="revanced_replace_navigation_upgrade_button_summary">Replaces the Upgrade button with the Settings button.</string>
    <string name="revanced_replace_navigation_upgrade_button_title">Replace Upgrade button</string>
    <string name="revanced_spoof_app_version_target_entry_7_17_52">7.17.52 - Comments section does not appear in home feed</string>
    <string name="revanced_spoof_app_version_target_invalid_toast">Invalid spoof app version: %s.</string>
    <string name="revanced_spoof_player_parameter_summary">"Spoof the player parameter to prevent playback issues.

Side effect:
• Sometimes the subtitles are located at the top of the player instead of the bottom."</string>
    <string name="revanced_spoof_player_parameter_title">Spoof player parameter</string>
    <string name="revanced_spoof_streaming_data_stats_for_nerds_summary">Shows the client used to fetch streaming data in Stats for nerds.</string>
    <string name="revanced_spoof_streaming_data_stats_for_nerds_title">Show in Stats for nerds</string>
    <string name="revanced_spoof_streaming_data_summary">"Spoof the streaming data to prevent playback issues.

• When used with 'Spoof client', playback issues may occur."</string>
    <string name="revanced_spoof_streaming_data_title">Spoof streaming data</string>
</resources>
