<?xml version='1.0' encoding='utf-8'?>
<resources>
    <string name="revanced_hide_action_button_index_summary_off">"Action buttons are hidden by identifier filter.

Info:
• Right action buttons are hidden.
• Hiding action buttons leaves empty space."</string>
    <string name="revanced_hide_action_button_index_summary_on">"Action buttons are hidden by index.

Info:
• Wrong action buttons may be hidden, or action buttons may not be hidden.
• Hiding action buttons leaves no empty space."</string>
    <string name="revanced_hide_action_button_index_title">Hide action button by index</string>
    <string name="revanced_remix_button_index_title">Remix button index</string>
</resources>